ps_fuzz/__init__.py
ps_fuzz/__main__.py
ps_fuzz/app_config.py
ps_fuzz/attack_config.py
ps_fuzz/attack_loader.py
ps_fuzz/attack_registry.py
ps_fuzz/chat_clients.py
ps_fuzz/cli.py
ps_fuzz/client_config.py
ps_fuzz/interactive_chat.py
ps_fuzz/interactive_mode.py
ps_fuzz/langchain_integration.py
ps_fuzz/logo.py
ps_fuzz/prompt_injection_fuzzer.py
ps_fuzz/ps_logging.py
ps_fuzz/results_table.py
ps_fuzz/test_base.py
ps_fuzz/util.py
ps_fuzz/work_progress_pool.py
ps_fuzz/attack_data/custom_benchmark1.csv
ps_fuzz/attack_data/custom_benchmark2.csv
ps_fuzz/attack_data/harmful_behavior.csv
ps_fuzz/attack_data/prompt_injections_for_base64.parquet
ps_fuzz/attacks/__init__.py
ps_fuzz/attacks/aim.py
ps_fuzz/attacks/base64_injection.py
ps_fuzz/attacks/complimentary_transition.py
ps_fuzz/attacks/custom_benchmark.py
ps_fuzz/attacks/dan.py
ps_fuzz/attacks/dynamic_test.py
ps_fuzz/attacks/ethical_compliance.py
ps_fuzz/attacks/harmful_behavior.py
ps_fuzz/attacks/self_refine.py
ps_fuzz/attacks/translation.py
ps_fuzz/attacks/typoglycemia.py
ps_fuzz/attacks/ucar.py
ps_fuzz/attacks/utils.py
tests/__init__.py
tests/test_chat_clients.py
tests/test_is_response_list.py
prompt_security_fuzzer-2.0.0.dist-info/LICENSE
prompt_security_fuzzer-2.0.0.dist-info/METADATA
prompt_security_fuzzer-2.0.0.dist-info/WHEEL
prompt_security_fuzzer-2.0.0.dist-info/entry_points.txt
prompt_security_fuzzer-2.0.0.dist-info/top_level.txt
prompt_security_fuzzer-2.0.0.dist-info/RECORD
