Metadata-Version: 2.1
Name: prompt-security-fuzzer
Version: 2.0.0
Summary: LLM and System Prompt vulnerability scanner tool
Home-page: https://github.com/prompt-security/ps-fuzz
Author: Prompt Security
Author-email: support@prompt.security
License: MIT
Classifier: Development Status :: 5 - Production/Stable
Classifier: Intended Audience :: Developers
Classifier: Topic :: Software Development :: Quality Assurance
Classifier: License :: OSI Approved :: MIT License
Classifier: Programming Language :: Python :: 3
Classifier: Programming Language :: Python :: 3.7
Classifier: Programming Language :: Python :: 3.8
Classifier: Programming Language :: Python :: 3.9
Classifier: Programming Language :: Python :: 3.10
Classifier: Programming Language :: Python :: 3.11
Requires-Python: >=3.7
License-File: LICENSE
Requires-Dist: openai ==1.6.1
Requires-Dist: langchain ==0.0.353
Requires-Dist: langchain-community ==0.0.7
Requires-Dist: langchain-core ==0.1.4
Requires-Dist: argparse ==1.4.0
Requires-Dist: python-dotenv ==1.0.0
Requires-Dist: tqdm ==4.66.1
Requires-Dist: colorama ==0.4.6
Requires-Dist: prettytable ==3.10.0
Requires-Dist: pandas ==2.2.2
Requires-Dist: inquirer ==3.2.4
Requires-Dist: prompt-toolkit ==3.0.43
Requires-Dist: fastparquet ==2024.2.0
Provides-Extra: dev
Requires-Dist: pytest ==7.4.4 ; extra == 'dev'
